odoo/addons/web_set_single_page_hidden/README.rst
odoo/addons/web_set_single_page_hidden/__init__.py
odoo/addons/web_set_single_page_hidden/__manifest__.py
odoo/addons/web_set_single_page_hidden/i18n/pt_BR.po
odoo/addons/web_set_single_page_hidden/i18n/web_set_single_page_hidden.pot
odoo/addons/web_set_single_page_hidden/readme/CONTRIBUTORS.rst
odoo/addons/web_set_single_page_hidden/readme/DESCRIPTION.rst
odoo/addons/web_set_single_page_hidden/static/description/icon.png
odoo/addons/web_set_single_page_hidden/static/description/index.html
odoo/addons/web_set_single_page_hidden/static/src/js/pager.js
odoo/addons/web_set_single_page_hidden/static/src/js/relational_fields.js
odoo/addons/web_set_single_page_hidden/views/webclient_templates.xml
odoo12_addon_web_set_single_page_hidden-12.0.1.0.0.99.dev5.dist-info/METADATA
odoo12_addon_web_set_single_page_hidden-12.0.1.0.0.99.dev5.dist-info/WHEEL
odoo12_addon_web_set_single_page_hidden-12.0.1.0.0.99.dev5.dist-info/top_level.txt
odoo12_addon_web_set_single_page_hidden-12.0.1.0.0.99.dev5.dist-info/RECORD
